LICENSE
MANIFEST.in
README.rst
demo_ezchat.ipynb
setup.cfg
setup.py
ezchat/__init__.py
ezchat/__meta__.py
ezchat/client.py
ezchat/gunicorn_conf.py
ezchat/hub.py
ezchat/servers.py
ezchat.egg-info/PKG-INFO
ezchat.egg-info/SOURCES.txt
ezchat.egg-info/dependency_links.txt
ezchat.egg-info/requires.txt
ezchat.egg-info/top_level.txt
ezchat/chatbox/.babelrc
ezchat/chatbox/index.html
ezchat/chatbox/package.json
ezchat/chatbox/webpack.config.js
ezchat/chatbox/dist/.DS_Store
ezchat/chatbox/dist/index.html
ezchat/chatbox/dist/assets/.DS_Store
ezchat/chatbox/dist/assets/app.js
ezchat/chatbox/dist/assets/app.js.gz
ezchat/chatbox/dist/assets/favicon.ico
ezchat/chatbox/dist/assets/index.html
ezchat/chatbox/dist/assets/font/fontawesome-webfont.eot
ezchat/chatbox/dist/assets/font/fontawesome-webfont.svg
ezchat/chatbox/dist/assets/font/fontawesome-webfont.ttf
ezchat/chatbox/dist/assets/font/fontawesome-webfont.woff
ezchat/chatbox/dist/assets/font/fontawesome-webfont.woff2
ezchat/chatbox/dist/assets/font/glyphicons-halflings-regular.eot
ezchat/chatbox/dist/assets/font/glyphicons-halflings-regular.svg
ezchat/chatbox/dist/assets/font/glyphicons-halflings-regular.ttf
ezchat/chatbox/dist/assets/font/glyphicons-halflings-regular.woff
ezchat/chatbox/dist/assets/font/glyphicons-halflings-regular.woff2
ezchat/chatbox/dist/assets/style/app-less.css
ezchat/chatbox/dist/assets/style/app-less.css.map
ezchat/chatbox/dist/assets/style/app.css
ezchat/chatbox/dist/assets/style/app.css.gz
ezchat/chatbox/dist/assets/style/app.css.map
ezchat/chatbox/src/.DS_Store
ezchat/chatbox/src/main.js
ezchat/chatbox/src/top.html
ezchat/chatbox/src/components/App/component.html
ezchat/chatbox/src/components/App/component.js
ezchat/chatbox/src/components/App/component.less
ezchat/chatbox/src/components/App/component.vue
ezchat/chatbox/src/components/ChatBox/component.html
ezchat/chatbox/src/components/ChatBox/component.js
ezchat/chatbox/src/components/ChatBox/component.less
ezchat/chatbox/src/components/ChatBox/component.vue
ezchat/chatbox/src/components/ChatLine/component.html
ezchat/chatbox/src/components/ChatLine/component.js
