Metadata-Version: 1.1
Name: ezchat
Version: 0.0.8
Summary: easy instant chat webapp
Home-page: https://gitlab.com/oscar6echo/ezchat
Author: oscar6echo
Author-email: olivier.borderies@gmail.com
License: MIT
Download-URL: https://gitlab.com/oscar6echo/ezchat/repository/archive.tar.gz?ref=0.0.8
Keywords: chat,notebook,javascript,vuejs
Platform: UNKNOWN
Classifier: Development Status :: 4 - Beta
Classifier: License :: OSI Approved :: MIT License
Classifier: Programming Language :: Python :: 3.5
Classifier: Programming Language :: Python :: 3.6
